elecsim
run
test
