Metadata-Version: 1.1
Name: elecsim
Version: 0.1.83
Summary: Agent-based Model for Electricity Markets
Home-page: https://github.com/alexanderkell/elecsim
Author: Alexander Kell
Author-email: alexander@kell.es
License: MIT
Download-URL: https://github.com/alexanderkell/elecsim/archive/0.1.1.1.tar.gz
Keywords: ElecSIM,Agent-based,Electricity,Market,Model,Simulation
Platform: UNKNOWN
Classifier: Development Status :: 4 - Beta
Classifier: Intended Audience :: Developers
Classifier: Topic :: Software Development :: Build Tools
Classifier: License :: OSI Approved :: MIT License
Classifier: Programming Language :: Python :: 3
Classifier: Programming Language :: Python :: 3.4
Classifier: Programming Language :: Python :: 3.5
Classifier: Programming Language :: Python :: 3.6
Classifier: Programming Language :: Python :: 3.7
